nrquery.py
nrquery-1.6.dist-info/LICENSE
nrquery-1.6.dist-info/METADATA
nrquery-1.6.dist-info/WHEEL
nrquery-1.6.dist-info/top_level.txt
nrquery-1.6.dist-info/RECORD
