Metadata-Version: 2.1
Name: nrquery
Version: 1.6
Summary: New Relic query interface
Home-page: https://github.com/vulogov/nrquery
Author: Vladimir Ulogov
Author-email: vladimir.ulogov@me.com
License: MIT
Platform: UNKNOWN
Classifier: License :: OSI Approved :: MIT License
Classifier: Programming Language :: Python :: 3
Classifier: Programming Language :: Python :: 3 :: Only
Classifier: Programming Language :: Python :: 3.8
Classifier: Programming Language :: Python :: 3.9
Classifier: Programming Language :: Python :: 3.10
Classifier: Programming Language :: Python :: Implementation :: CPython
Requires-Python: >=3.8
License-File: LICENSE
